conflateddict/__init__.py
conflateddict/batchdict.py
conflateddict/conflateddict.py
conflateddict/lambdadict.py
conflateddict/meandict.py
conflateddict/modedict.py
conflateddict/ohlcdict.py
conflateddict-0.1.2.dist-info/METADATA
conflateddict-0.1.2.dist-info/RECORD
conflateddict-0.1.2.dist-info/WHEEL
conflateddict-0.1.2.dist-info/top_level.txt
