Metadata-Version: 2.1
Name: conflateddict
Version: 0.1.2
Summary: Classes to help conflate streaming data.
Home-page: https://github.com/christianreimer/conflateddict
Author: Christian Reimer
Author-email: christian.reimer@gmail.com
License: UNKNOWN
Platform: UNKNOWN
Classifier: Development Status :: 3 - Alpha
Classifier: Programming Language :: Python
Classifier: Programming Language :: Python :: 3
Classifier: Programming Language :: Python :: 3.6
Classifier: Programming Language :: Python :: 3.7
Classifier: License :: OSI Approved :: MIT License
